LoceZap/__init__.py
LoceZap/__init__.pyi
LoceZap/py.typed
loce_zap/__init__.py
loce_zap/client.py
loce_zap/exceptions.py
loce_zap/http.py
loce_zap/py.typed
loce_zap/response.py
loce_zap/types.py
loce_zap/webhooks.py
loce_zap/resources/__init__.py
loce_zap/resources/messages.py
loce_zap/resources/sessions.py
loce_zap-0.2.5.dist-info/METADATA
loce_zap-0.2.5.dist-info/WHEEL
loce_zap-0.2.5.dist-info/top_level.txt
loce_zap-0.2.5.dist-info/RECORD
