Metadata-Version: 2.4
Name: loce-zap
Version: 0.2.5
Summary: Official Python SDK for the Loce Zap API
Author-email: Loce <dev@loce.com>
License: MIT
Requires-Python: >=3.9
Requires-Dist: httpx<1.0,>=0.27
Requires-Dist: typing-extensions>=4.7
